CHANGELOG.md
gadk/__init__.py
gadk/cli.py
gadk/constants.py
gadk/elements.py
gadk/utils.py
gadk-0.3.0.dist-info/entry_points.txt
gadk-0.3.0.dist-info/LICENSE
gadk-0.3.0.dist-info/WHEEL
gadk-0.3.0.dist-info/METADATA
gadk-0.3.0.dist-info/RECORD
