Metadata-Version: 2.1
Name: gadk
Version: 0.3.0
Summary: Unofficial Github Actions Development Kit
Home-page: https://github.com/maartenJacobs/gadk
License: MIT
Author: Maarten Jacobs
Author-email: maarten.j.jacobs@gmail.com
Requires-Python: >=3.6,<4
Classifier: License :: OSI Approved :: MIT License
Classifier: Programming Language :: Python :: 3
Classifier: Programming Language :: Python :: 3.6
Classifier: Programming Language :: Python :: 3.7
Classifier: Programming Language :: Python :: 3.8
Requires-Dist: click (>=7.1.1,<8.0.0)
Requires-Dist: colorama (>=0.4.3,<0.5.0)
Requires-Dist: pyyaml (>=5.3,<6.0)
Project-URL: Repository, https://github.com/maartenJacobs/gadk
